infi.monotonic_time-0.1.9-py2.7-nspkg.pth
infi/monotonic_time/__init__.py
infi/monotonic_time/__version__.py
infi/monotonic_time/darwin.py
infi/monotonic_time/linux.py
infi.monotonic_time-0.1.9.dist-info/LICENSE
infi.monotonic_time-0.1.9.dist-info/METADATA
infi.monotonic_time-0.1.9.dist-info/WHEEL
infi.monotonic_time-0.1.9.dist-info/entry_points.txt
infi.monotonic_time-0.1.9.dist-info/namespace_packages.txt
infi.monotonic_time-0.1.9.dist-info/top_level.txt
infi.monotonic_time-0.1.9.dist-info/RECORD
